setup.py
hot/__init__.py
hot/lint.py
hot/shell.py
hot.egg-info/PKG-INFO
hot.egg-info/SOURCES.txt
hot.egg-info/dependency_links.txt
hot.egg-info/entry_points.txt
hot.egg-info/requires.txt
hot.egg-info/top_level.txt
hot/tests/__init__.py
hot/tests/fab.py
hot/tests/script.py
hot/utils/__init__.py
hot/utils/auth.py
hot/utils/files.py
hot/utils/hosts.py
hot/utils/repo.py
hot/utils/string.py
hot/utils/test.py
hot/utils/timeout.py
hot/utils/token.py
hot/utils/yaml.py