Metadata-Version: 1.1
Name: hot
Version: 0.5.8
Summary: Heat author command-line utility
Home-page: https://github.com/heat-tools/hot
Author: Rackspace
Author-email: brint.ohearn@rackspace.com
License: Apache License (2.0)
Keywords: heat orchestration configuration automation rackspace openstack
Platform: UNKNOWN
Classifier: Programming Language :: Python
